uadapy/__init__.py
uadapy/distribution.py
uadapy/timeseries.py
uadapy/data/__init__.py
uadapy/data/data.py
uadapy/distributions/chi_square_comb.py
uadapy/dr/__init__.py
uadapy/dr/uamds.py
uadapy/dr/uapca.py
uadapy/plotting/__init__.py
uadapy/plotting/distribution_plot.py
uadapy/plotting/interactive_splom.py
uadapy/plotting/plots_1d.py
uadapy/plotting/plots_2d.py
uadapy/plotting/plots_nd.py
uadapy/plotting/plots_timeseries.py
uadapy/plotting/shepard_diagram.py
uadapy/plotting/utils.py
uadapy/temporal/spectralAnalysis.py
uadapy/temporal/uastl.py
uadapy/temporal/chi2comb/chi2comb.dll
uadapy/temporal/chi2comb/interface.h
uadapy/temporal/chi2comb/libchi2comb.dylib
uadapy/temporal/chi2comb/libchi2comb.so
uadapy-0.1.0.dist-info/licenses/LICENSE
uadapy-0.1.0.dist-info/METADATA
uadapy-0.1.0.dist-info/WHEEL
uadapy-0.1.0.dist-info/top_level.txt
uadapy-0.1.0.dist-info/RECORD
