Metadata-Version: 2.4
Name: uadapy
Version: 0.1.0
Summary: A software package for uncertainty-aware data analysis with Python
Author: David Hägele, Marina Evers, Patrick Paetzold, Ruben Bauer, Nikhil Bhavikatti
License: MIT License
Project-URL: Homepage, https://github.com/UniStuttgart-VISUS/uadapy
Project-URL: Bug Tracker, https://github.com/UniStuttgart-VISUS/uadapy/issues
Classifier: Programming Language :: Python :: 3
Classifier: License :: OSI Approved :: MIT License
Classifier: Operating System :: OS Independent
Requires-Python: >=3.10
License-File: LICENSE
Requires-Dist: numpy
Requires-Dist: scipy
Requires-Dist: matplotlib
Requires-Dist: scikit-learn
Requires-Dist: numba
Requires-Dist: glasbey
Requires-Dist: seaborn
Requires-Dist: cffi
Dynamic: license-file
